CHANGELOG.md
LICENSE
README.md
pyfsm_tool/__init__.py
pyfsm_tool/finite_state_machine.py
pyfsm_tool/fsm_exceptions.py
pyfsm_tool/state_behaviour.py
pyfsm_tool-0.9.3.dist-info/LICENSE
pyfsm_tool-0.9.3.dist-info/METADATA
pyfsm_tool-0.9.3.dist-info/WHEEL
pyfsm_tool-0.9.3.dist-info/RECORD
