Metadata-Version: 2.1
Name: pyfsm-tool
Version: 0.9.3
Summary: pyfsm-tool is a module to create and manipulate finite states machines.
Home-page: https://github.com/DevAI-64/pyfsm-tool
License: MIT
Keywords: fsm,pyfsm,pyfsm-tool,state,states,transition,transitions,fintite state machine,fintite states machine,finite states machines,graph,pygraph,pygraph-tool
Author: BEL AICH David
Author-email: belaich.david@outlook.fr
Maintainer: BEL AICH David
Maintainer-email: belaich.david@outlook.fr
Requires-Python: >=3.8.1,<4.0.0
Classifier: Development Status :: 5 - Production/Stable
Classifier: License :: OSI Approved :: MIT License
Classifier: Programming Language :: Python :: 3
Classifier: Programming Language :: Python :: 3.9
Classifier: Programming Language :: Python :: 3.10
Classifier: Programming Language :: Python :: 3.11
Classifier: Programming Language :: Python :: 3
Classifier: Topic :: Scientific/Engineering
Requires-Dist: pygraph-tool (>=0.9.0,<0.10.0)
Project-URL: Repository, https://github.com/DevAI-64/pyfsm-tool
